gradebook/__init__.py
gradebook/grade_utils.py
gradebook/save_grades.py
CI_CD_Demo_Grade_Project-0.1.dist-info/LICENSE
CI_CD_Demo_Grade_Project-0.1.dist-info/METADATA
CI_CD_Demo_Grade_Project-0.1.dist-info/WHEEL
CI_CD_Demo_Grade_Project-0.1.dist-info/top_level.txt
CI_CD_Demo_Grade_Project-0.1.dist-info/RECORD
