Metadata-Version: 2.1
Name: CI_CD_Demo_Grade_Project
Version: 0.1
Summary: CI/CD Demonstration Project
Author-email: Katarzyna Rachwal <krachwal3@gatech.edu>
License: MIT License
License-File: LICENSE
